tarpy/__init__.py
tarpy/config.py
tarpy/filters.py
tarpy/logger.py
tarpy/tarhandler.py
tarpy/utils.py
tarpy/cli/__init__.py
tarpy/cli/run.py
tarpy-0.0.5.dist-info/LICENSE
tarpy-0.0.5.dist-info/METADATA
tarpy-0.0.5.dist-info/WHEEL
tarpy-0.0.5.dist-info/entry_points.txt
tarpy-0.0.5.dist-info/top_level.txt
tarpy-0.0.5.dist-info/RECORD
